navmplot/__init__.py
navmplot/color_dicts.py
navmplot/naver_maps_templates.py
navmplot/navmplot.py
navmplot/markers/000000.png
navmplot/markers/000080.png
navmplot/markers/00008B.png
navmplot/markers/0000CD.png
navmplot/markers/0000FF.png
navmplot/markers/006400.png
navmplot/markers/008000.png
navmplot/markers/008080.png
navmplot/markers/008B8B.png
navmplot/markers/00BFFF.png
navmplot/markers/00CED1.png
navmplot/markers/00FA9A.png
navmplot/markers/00FF00.png
navmplot/markers/00FF7F.png
navmplot/markers/00FFFF.png
navmplot/markers/191970.png
navmplot/markers/1E90FF.png
navmplot/markers/20B2AA.png
navmplot/markers/228B22.png
navmplot/markers/2E8B57.png
navmplot/markers/2F4F4F.png
navmplot/markers/32CD32.png
navmplot/markers/3CB371.png
navmplot/markers/40E0D0.png
navmplot/markers/4169E1.png
navmplot/markers/4682B4.png
navmplot/markers/483D8B.png
navmplot/markers/48D1CC.png
navmplot/markers/4B0082.png
navmplot/markers/556B2F.png
navmplot/markers/5F9EA0.png
navmplot/markers/6495ED.png
navmplot/markers/66CDAA.png
navmplot/markers/696969.png
navmplot/markers/6A5ACD.png
navmplot/markers/6B8E23.png
navmplot/markers/708090.png
navmplot/markers/778899.png
navmplot/markers/7B68EE.png
navmplot/markers/7CFC00.png
navmplot/markers/7FFF00.png
navmplot/markers/7FFFD4.png
navmplot/markers/800000.png
navmplot/markers/800080.png
navmplot/markers/808000.png
navmplot/markers/808080.png
navmplot/markers/87CEEB.png
navmplot/markers/87CEFA.png
navmplot/markers/8A2BE2.png
navmplot/markers/8B0000.png
navmplot/markers/8B008B.png
navmplot/markers/8B4513.png
navmplot/markers/8FBC8F.png
navmplot/markers/90EE90.png
navmplot/markers/9370DB.png
navmplot/markers/9400D3.png
navmplot/markers/98FB98.png
navmplot/markers/9932CC.png
navmplot/markers/9ACD32.png
navmplot/markers/A0522D.png
navmplot/markers/A52A2A.png
navmplot/markers/A9A9A9.png
navmplot/markers/ADD8E6.png
navmplot/markers/ADFF2F.png
navmplot/markers/AFEEEE.png
navmplot/markers/B0C4DE.png
navmplot/markers/B0E0E6.png
navmplot-0.2.1.dist-info/LICENSE
navmplot-0.2.1.dist-info/METADATA
navmplot-0.2.1.dist-info/WHEEL
navmplot-0.2.1.dist-info/top_level.txt
navmplot-0.2.1.dist-info/RECORD
