Metadata-Version: 2.1
Name: navmplot
Version: 0.2.1
Summary: Provide a interface to plotting data with Naver Maps with Python
Home-page: https://github.com/yycen/navmplot
Author: Yuanyuan Cen
Author-email: yycen@live.com
License: MIT
Keywords: python wrapper naver maps
Platform: UNKNOWN
Requires-Dist: requests
